immich_python_sdk/__init__.py
immich_python_sdk/api_client.py
immich_python_sdk/api_response.py
immich_python_sdk/configuration.py
immich_python_sdk/exceptions.py
immich_python_sdk/py.typed
immich_python_sdk/rest.py
immich_python_sdk/api/__init__.py
immich_python_sdk/api/activities_api.py
immich_python_sdk/api/albums_api.py
immich_python_sdk/api/api_keys_api.py
immich_python_sdk/api/assets_api.py
immich_python_sdk/api/authentication_api.py
immich_python_sdk/api/deprecated_api.py
immich_python_sdk/api/download_api.py
immich_python_sdk/api/duplicates_api.py
immich_python_sdk/api/faces_api.py
immich_python_sdk/api/jobs_api.py
immich_python_sdk/api/libraries_api.py
immich_python_sdk/api/map_api.py
immich_python_sdk/api/memories_api.py
immich_python_sdk/api/notifications_admin_api.py
immich_python_sdk/api/notifications_api.py
immich_python_sdk/api/o_auth_api.py
immich_python_sdk/api/partners_api.py
immich_python_sdk/api/people_api.py
immich_python_sdk/api/search_api.py
immich_python_sdk/api/server_api.py
immich_python_sdk/api/sessions_api.py
immich_python_sdk/api/shared_links_api.py
immich_python_sdk/api/stacks_api.py
immich_python_sdk/api/sync_api.py
immich_python_sdk/api/system_config_api.py
immich_python_sdk/api/system_metadata_api.py
immich_python_sdk/api/tags_api.py
immich_python_sdk/api/timeline_api.py
immich_python_sdk/api/trash_api.py
immich_python_sdk/api/users_admin_api.py
immich_python_sdk/api/users_api.py
immich_python_sdk/api/view_api.py
immich_python_sdk/models/__init__.py
immich_python_sdk/models/activity_create_dto.py
immich_python_sdk/models/activity_response_dto.py
immich_python_sdk/models/activity_statistics_response_dto.py
immich_python_sdk/models/add_users_dto.py
immich_python_sdk/models/admin_onboarding_update_dto.py
immich_python_sdk/models/album_response_dto.py
immich_python_sdk/models/album_statistics_response_dto.py
immich_python_sdk/models/album_user_add_dto.py
immich_python_sdk/models/album_user_create_dto.py
immich_python_sdk-1.134.0.dist-info/METADATA
immich_python_sdk-1.134.0.dist-info/WHEEL
immich_python_sdk-1.134.0.dist-info/top_level.txt
immich_python_sdk-1.134.0.dist-info/RECORD
