Metadata-Version: 2.4
Name: immich-python-sdk
Version: 1.134.0
Summary: Immich
Home-page: https://github.com/Marian-Braendle/immich-python-sdk/tree/immich-v1.134.0
Author: OpenAPI Generator community
Author-email: team@openapitools.org
License: MIT
Keywords: OpenAPI,OpenAPI-Generator,Immich
Requires-Dist: urllib3<3.0.0,>=2.1.0
Requires-Dist: python-dateutil>=2.8.2
Requires-Dist: pydantic>=2
Requires-Dist: typing-extensions>=4.7.1
Dynamic: author
Dynamic: author-email
Dynamic: description
Dynamic: description-content-type
Dynamic: home-page
Dynamic: keywords
Dynamic: license
Dynamic: requires-dist
Dynamic: summary
